{
  "Version": "1.0",
  "Parameters": {
    "RuleName": "rdsapsql003-cluster-default-admin-check",
    "Description": "Checks if an Amazon Relational Database Service (Amazon RDS) database cluster has changed the admin username from its default value. The rule is NON_COMPLIANT if the admin username is set to the default value.",
    "SourceRuntime": null,
    "CodeKey": null,
    "InputParameters": "{}",
    "OptionalParameters": "{}",
    "SourceEvents": "AWS::RDS::DBCluster",
    "SourceIdentifier": "RDS_CLUSTER_DEFAULT_ADMIN_CHECK"
  },
  "Tags": "[]"
}